pipenv_pex/__init__.py
pipenv_pex/pipenv_pex.py
pipenv_pex-0.2.3.dist-info/DESCRIPTION.rst
pipenv_pex-0.2.3.dist-info/METADATA
pipenv_pex-0.2.3.dist-info/RECORD
pipenv_pex-0.2.3.dist-info/WHEEL
pipenv_pex-0.2.3.dist-info/entry_points.txt
pipenv_pex-0.2.3.dist-info/metadata.json
pipenv_pex-0.2.3.dist-info/top_level.txt
