Metadata-Version: 2.0
Name: pipenv-pex
Version: 0.2.3
Summary: Generate Python executable files via PEX using info from Pipfile
Home-page: https://github.com/it-is-wednesday/pipenv-pex
Author: Maor Kadosh
License: UNKNOWN
Platform: UNKNOWN
Classifier: Programming Language :: Python :: 3
Classifier: License :: OSI Approved :: GNU Affero General Public License v3 or later (AGPLv3+)
Classifier: Operating System :: OS Independent
Requires-Python: >=3.5
Requires-Dist: click
Requires-Dist: colorama
Requires-Dist: pex
Requires-Dist: pipenv
